[
  {
    "login": "vienna-rb",
    "id": 3541331,
    "url": "https://api.github.com/orgs/vienna-rb",
    "repos_url": "https://api.github.com/orgs/vienna-rb/repos",
    "events_url": "https://api.github.com/orgs/vienna-rb/events",
    "hooks_url": "https://api.github.com/orgs/vienna-rb/hooks",
    "issues_url": "https://api.github.com/orgs/vienna-rb/issues",
    "members_url": "https://api.github.com/orgs/vienna-rb/members{/member}",
    "public_members_url": "https://api.github.com/orgs/vienna-rb/public_members{/member}",
    "avatar_url": "https://avatars.githubusercontent.com/u/3541331?v=3",
    "description": null
  },
  {
    "login": "openbeer",
    "id": 4464191,
    "url": "https://api.github.com/orgs/openbeer",
    "repos_url": "https://api.github.com/orgs/openbeer/repos",
    "events_url": "https://api.github.com/orgs/openbeer/events",
    "hooks_url": "https://api.github.com/orgs/openbeer/hooks",
    "issues_url": "https://api.github.com/orgs/openbeer/issues",
    "members_url": "https://api.github.com/orgs/openbeer/members{/member}",
    "public_members_url": "https://api.github.com/orgs/openbeer/public_members{/member}",
    "avatar_url": "https://avatars.githubusercontent.com/u/4464191?v=3",
    "description": "Open Public Domain Beer, Brewery n Brewpub Data"
  },
  {
    "login": "slideshow-s9",
    "id": 4464373,
    "url": "https://api.github.com/orgs/slideshow-s9",
    "repos_url": "https://api.github.com/orgs/slideshow-s9/repos",
    "events_url": "https://api.github.com/orgs/slideshow-s9/events",
    "hooks_url": "https://api.github.com/orgs/slideshow-s9/hooks",
    "issues_url": "https://api.github.com/orgs/slideshow-s9/issues",
    "members_url": "https://api.github.com/orgs/slideshow-s9/members{/member}",
    "public_members_url": "https://api.github.com/orgs/slideshow-s9/public_members{/member}",
    "avatar_url": "https://avatars.githubusercontent.com/u/4464373?v=3",
    "description": "Free Web Alternative to PowerPoint and Keynote Using Easy-to-Write and Easy-to-Read Plain Text Wiki-Style Markup"
  },
  {
    "login": "openfootball",
    "id": 4477026,
    "url": "https://api.github.com/orgs/openfootball",
    "repos_url": "https://api.github.com/orgs/openfootball/repos",
    "events_url": "https://api.github.com/orgs/openfootball/events",
    "hooks_url": "https://api.github.com/orgs/openfootball/hooks",
    "issues_url": "https://api.github.com/orgs/openfootball/issues",
    "members_url": "https://api.github.com/orgs/openfootball/members{/member}",
    "public_members_url": "https://api.github.com/orgs/openfootball/public_members{/member}",
    "avatar_url": "https://avatars.githubusercontent.com/u/4477026?v=3",
    "description": "Open Public Domain Football Data"
  },
  {
    "login": "webstart",
    "id": 4519022,
    "url": "https://api.github.com/orgs/webstart",
    "repos_url": "https://api.github.com/orgs/webstart/repos",
    "events_url": "https://api.github.com/orgs/webstart/events",
    "hooks_url": "https://api.github.com/orgs/webstart/hooks",
    "issues_url": "https://api.github.com/orgs/webstart/issues",
    "members_url": "https://api.github.com/orgs/webstart/members{/member}",
    "public_members_url": "https://api.github.com/orgs/webstart/public_members{/member}",
    "avatar_url": "https://avatars.githubusercontent.com/u/4519022?v=3",
    "description": "Run Ruby Web Apps w/ Java (Includes Auto-Updater)"
  },
  {
    "login": "openbookie",
    "id": 5358335,
    "url": "https://api.github.com/orgs/openbookie",
    "repos_url": "https://api.github.com/orgs/openbookie/repos",
    "events_url": "https://api.github.com/orgs/openbookie/events",
    "hooks_url": "https://api.github.com/orgs/openbookie/hooks",
    "issues_url": "https://api.github.com/orgs/openbookie/issues",
    "members_url": "https://api.github.com/orgs/openbookie/members{/member}",
    "public_members_url": "https://api.github.com/orgs/openbookie/public_members{/member}",
    "avatar_url": "https://avatars.githubusercontent.com/u/5358335?v=3",
    "description": "Free Sports (Football) Betting (Picks, Predictions) Pool Manager"
  },
  {
    "login": "openmundi",
    "id": 5459882,
    "url": "https://api.github.com/orgs/openmundi",
    "repos_url": "https://api.github.com/orgs/openmundi/repos",
    "events_url": "https://api.github.com/orgs/openmundi/events",
    "hooks_url": "https://api.github.com/orgs/openmundi/hooks",
    "issues_url": "https://api.github.com/orgs/openmundi/issues",
    "members_url": "https://api.github.com/orgs/openmundi/members{/member}",
    "public_members_url": "https://api.github.com/orgs/openmundi/public_members{/member}",
    "avatar_url": "https://avatars.githubusercontent.com/u/5459882?v=3",
    "description": "Open Public Domain World Data (Countries, Regions, Cities, etc.)"
  },
  {
    "login": "opensport",
    "id": 5462176,
    "url": "https://api.github.com/orgs/opensport",
    "repos_url": "https://api.github.com/orgs/opensport/repos",
    "events_url": "https://api.github.com/orgs/opensport/events",
    "hooks_url": "https://api.github.com/orgs/opensport/hooks",
    "issues_url": "https://api.github.com/orgs/opensport/issues",
    "members_url": "https://api.github.com/orgs/opensport/members{/member}",
    "public_members_url": "https://api.github.com/orgs/opensport/public_members{/member}",
    "avatar_url": "https://avatars.githubusercontent.com/u/5462176?v=3",
    "description": "Open Public Domain Sports Data (American Football, Alpine Ski, Forumula 1, etc.)"
  },
  {
    "login": "feedreader",
    "id": 5468385,
    "url": "https://api.github.com/orgs/feedreader",
    "repos_url": "https://api.github.com/orgs/feedreader/repos",
    "events_url": "https://api.github.com/orgs/feedreader/events",
    "hooks_url": "https://api.github.com/orgs/feedreader/hooks",
    "issues_url": "https://api.github.com/orgs/feedreader/issues",
    "members_url": "https://api.github.com/orgs/feedreader/members{/member}",
    "public_members_url": "https://api.github.com/orgs/feedreader/public_members{/member}",
    "avatar_url": "https://avatars.githubusercontent.com/u/5468385?v=3",
    "description": "Free Planet (Static) Site Generator - Auto-Build Web Pages From Published Web Feeds"
  },
  {
    "login": "rubylibs",
    "id": 5468527,
    "url": "https://api.github.com/orgs/rubylibs",
    "repos_url": "https://api.github.com/orgs/rubylibs/repos",
    "events_url": "https://api.github.com/orgs/rubylibs/events",
    "hooks_url": "https://api.github.com/orgs/rubylibs/hooks",
    "issues_url": "https://api.github.com/orgs/rubylibs/issues",
    "members_url": "https://api.github.com/orgs/rubylibs/members{/member}",
    "public_members_url": "https://api.github.com/orgs/rubylibs/public_members{/member}",
    "avatar_url": "https://avatars.githubusercontent.com/u/5468527?v=3",
    "description": null
  },
  {
    "login": "sportlogos",
    "id": 5468717,
    "url": "https://api.github.com/orgs/sportlogos",
    "repos_url": "https://api.github.com/orgs/sportlogos/repos",
    "events_url": "https://api.github.com/orgs/sportlogos/events",
    "hooks_url": "https://api.github.com/orgs/sportlogos/hooks",
    "issues_url": "https://api.github.com/orgs/sportlogos/issues",
    "members_url": "https://api.github.com/orgs/sportlogos/members{/member}",
    "public_members_url": "https://api.github.com/orgs/sportlogos/public_members{/member}",
    "avatar_url": "https://avatars.githubusercontent.com/u/5468717?v=3",
    "description": null
  },
  {
    "login": "libsjs",
    "id": 5468911,
    "url": "https://api.github.com/orgs/libsjs",
    "repos_url": "https://api.github.com/orgs/libsjs/repos",
    "events_url": "https://api.github.com/orgs/libsjs/events",
    "hooks_url": "https://api.github.com/orgs/libsjs/hooks",
    "issues_url": "https://api.github.com/orgs/libsjs/issues",
    "members_url": "https://api.github.com/orgs/libsjs/members{/member}",
    "public_members_url": "https://api.github.com/orgs/libsjs/public_members{/member}",
    "avatar_url": "https://avatars.githubusercontent.com/u/5468911?v=3",
    "description": "Free JavaScript Libraries"
  },
  {
    "login": "textkit",
    "id": 6266443,
    "url": "https://api.github.com/orgs/textkit",
    "repos_url": "https://api.github.com/orgs/textkit/repos",
    "events_url": "https://api.github.com/orgs/textkit/events",
    "hooks_url": "https://api.github.com/orgs/textkit/hooks",
    "issues_url": "https://api.github.com/orgs/textkit/issues",
    "members_url": "https://api.github.com/orgs/textkit/members{/member}",
    "public_members_url": "https://api.github.com/orgs/textkit/public_members{/member}",
    "avatar_url": "https://avatars.githubusercontent.com/u/6266443?v=3",
    "description": "Better Comma-Separated Values (CSV) Format, and Much More"
  },
  {
    "login": "openwine",
    "id": 6531634,
    "url": "https://api.github.com/orgs/openwine",
    "repos_url": "https://api.github.com/orgs/openwine/repos",
    "events_url": "https://api.github.com/orgs/openwine/events",
    "hooks_url": "https://api.github.com/orgs/openwine/hooks",
    "issues_url": "https://api.github.com/orgs/openwine/issues",
    "members_url": "https://api.github.com/orgs/openwine/members{/member}",
    "public_members_url": "https://api.github.com/orgs/openwine/public_members{/member}",
    "avatar_url": "https://avatars.githubusercontent.com/u/6531634?v=3",
    "description": "Open Public Domain Wine & Winery Data"
  },
  {
    "login": "hybook",
    "id": 6699073,
    "url": "https://api.github.com/orgs/hybook",
    "repos_url": "https://api.github.com/orgs/hybook/repos",
    "events_url": "https://api.github.com/orgs/hybook/events",
    "hooks_url": "https://api.github.com/orgs/hybook/hooks",
    "issues_url": "https://api.github.com/orgs/hybook/issues",
    "members_url": "https://api.github.com/orgs/hybook/members{/member}",
    "public_members_url": "https://api.github.com/orgs/hybook/public_members{/member}",
    "avatar_url": "https://avatars.githubusercontent.com/u/6699073?v=3",
    "description": "Free Hypertext Book Generator & Templates"
  },
  {
    "login": "beerlabels",
    "id": 6749741,
    "url": "https://api.github.com/orgs/beerlabels",
    "repos_url": "https://api.github.com/orgs/beerlabels/repos",
    "events_url": "https://api.github.com/orgs/beerlabels/events",
    "hooks_url": "https://api.github.com/orgs/beerlabels/hooks",
    "issues_url": "https://api.github.com/orgs/beerlabels/issues",
    "members_url": "https://api.github.com/orgs/beerlabels/members{/member}",
    "public_members_url": "https://api.github.com/orgs/beerlabels/public_members{/member}",
    "avatar_url": "https://avatars.githubusercontent.com/u/6749741?v=3",
    "description": ""
  },
  {
    "login": "footballjs",
    "id": 7499790,
    "url": "https://api.github.com/orgs/footballjs",
    "repos_url": "https://api.github.com/orgs/footballjs/repos",
    "events_url": "https://api.github.com/orgs/footballjs/events",
    "hooks_url": "https://api.github.com/orgs/footballjs/hooks",
    "issues_url": "https://api.github.com/orgs/footballjs/issues",
    "members_url": "https://api.github.com/orgs/footballjs/members{/member}",
    "public_members_url": "https://api.github.com/orgs/footballjs/public_members{/member}",
    "avatar_url": "https://avatars.githubusercontent.com/u/7499790?v=3",
    "description": "Free Football Scripts n Templates using the football.db HTTP JSON API"
  },
  {
    "login": "beerkit",
    "id": 7508626,
    "url": "https://api.github.com/orgs/beerkit",
    "repos_url": "https://api.github.com/orgs/beerkit/repos",
    "events_url": "https://api.github.com/orgs/beerkit/events",
    "hooks_url": "https://api.github.com/orgs/beerkit/hooks",
    "issues_url": "https://api.github.com/orgs/beerkit/issues",
    "members_url": "https://api.github.com/orgs/beerkit/members{/member}",
    "public_members_url": "https://api.github.com/orgs/beerkit/public_members{/member}",
    "avatar_url": "https://avatars.githubusercontent.com/u/7508626?v=3",
    "description": "Open Beer, Brewery n Brewpub Data Tools & Scripts"
  },
  {
    "login": "rsssf",
    "id": 7706904,
    "url": "https://api.github.com/orgs/rsssf",
    "repos_url": "https://api.github.com/orgs/rsssf/repos",
    "events_url": "https://api.github.com/orgs/rsssf/events",
    "hooks_url": "https://api.github.com/orgs/rsssf/hooks",
    "issues_url": "https://api.github.com/orgs/rsssf/issues",
    "members_url": "https://api.github.com/orgs/rsssf/members{/member}",
    "public_members_url": "https://api.github.com/orgs/rsssf/public_members{/member}",
    "avatar_url": "https://avatars.githubusercontent.com/u/7706904?v=3",
    "description": "football.db RSSSF (Rec.Sport.Soccer Statistics Foundation) Archive Data"
  },
  {
    "login": "wikiscript",
    "id": 7778000,
    "url": "https://api.github.com/orgs/wikiscript",
    "repos_url": "https://api.github.com/orgs/wikiscript/repos",
    "events_url": "https://api.github.com/orgs/wikiscript/events",
    "hooks_url": "https://api.github.com/orgs/wikiscript/hooks",
    "issues_url": "https://api.github.com/orgs/wikiscript/issues",
    "members_url": "https://api.github.com/orgs/wikiscript/members{/member}",
    "public_members_url": "https://api.github.com/orgs/wikiscript/public_members{/member}",
    "avatar_url": "https://avatars.githubusercontent.com/u/7778000?v=3",
    "description": "Open Data Scripts for Wikipedia - Turn Free-Style (or Semi-Structured) Text into Structured Data"
  },
  {
    "login": "sportdb",
    "id": 7819219,
    "url": "https://api.github.com/orgs/sportdb",
    "repos_url": "https://api.github.com/orgs/sportdb/repos",
    "events_url": "https://api.github.com/orgs/sportdb/events",
    "hooks_url": "https://api.github.com/orgs/sportdb/hooks",
    "issues_url": "https://api.github.com/orgs/sportdb/issues",
    "members_url": "https://api.github.com/orgs/sportdb/members{/member}",
    "public_members_url": "https://api.github.com/orgs/sportdb/public_members{/member}",
    "avatar_url": "https://avatars.githubusercontent.com/u/7819219?v=3",
    "description": "Open Sport(s) Data (Football, Alpine Ski, Formula 1, etc.) Tools & Scripts"
  },
  {
    "login": "worlddb",
    "id": 7819489,
    "url": "https://api.github.com/orgs/worlddb",
    "repos_url": "https://api.github.com/orgs/worlddb/repos",
    "events_url": "https://api.github.com/orgs/worlddb/events",
    "hooks_url": "https://api.github.com/orgs/worlddb/hooks",
    "issues_url": "https://api.github.com/orgs/worlddb/issues",
    "members_url": "https://api.github.com/orgs/worlddb/members{/member}",
    "public_members_url": "https://api.github.com/orgs/worlddb/public_members{/member}",
    "avatar_url": "https://avatars.githubusercontent.com/u/7819489?v=3",
    "description": "Open World Data (Countries, Regions, Cities, etc.) Tools & Scripts"
  },
  {
    "login": "persondb",
    "id": 8015057,
    "url": "https://api.github.com/orgs/persondb",
    "repos_url": "https://api.github.com/orgs/persondb/repos",
    "events_url": "https://api.github.com/orgs/persondb/events",
    "hooks_url": "https://api.github.com/orgs/persondb/hooks",
    "issues_url": "https://api.github.com/orgs/persondb/issues",
    "members_url": "https://api.github.com/orgs/persondb/members{/member}",
    "public_members_url": "https://api.github.com/orgs/persondb/public_members{/member}",
    "avatar_url": "https://avatars.githubusercontent.com/u/8015057?v=3",
    "description": ""
  },
  {
    "login": "footballcsv",
    "id": 8245364,
    "url": "https://api.github.com/orgs/footballcsv",
    "repos_url": "https://api.github.com/orgs/footballcsv/repos",
    "events_url": "https://api.github.com/orgs/footballcsv/events",
    "hooks_url": "https://api.github.com/orgs/footballcsv/hooks",
    "issues_url": "https://api.github.com/orgs/footballcsv/issues",
    "members_url": "https://api.github.com/orgs/footballcsv/members{/member}",
    "public_members_url": "https://api.github.com/orgs/footballcsv/public_members{/member}",
    "avatar_url": "https://avatars.githubusercontent.com/u/8245364?v=3",
    "description": "Real Madrid, Manchester United, 3-1, 1-0"
  },
  {
    "login": "beercsv",
    "id": 8354011,
    "url": "https://api.github.com/orgs/beercsv",
    "repos_url": "https://api.github.com/orgs/beercsv/repos",
    "events_url": "https://api.github.com/orgs/beercsv/events",
    "hooks_url": "https://api.github.com/orgs/beercsv/hooks",
    "issues_url": "https://api.github.com/orgs/beercsv/issues",
    "members_url": "https://api.github.com/orgs/beercsv/members{/member}",
    "public_members_url": "https://api.github.com/orgs/beercsv/public_members{/member}",
    "avatar_url": "https://avatars.githubusercontent.com/u/8354011?v=3",
    "description": "Wiener Original, 5.3%, 12.3°, Ottakringer, Vienna Lager"
  },
  {
    "login": "sportkit",
    "id": 8416996,
    "url": "https://api.github.com/orgs/sportkit",
    "repos_url": "https://api.github.com/orgs/sportkit/repos",
    "events_url": "https://api.github.com/orgs/sportkit/events",
    "hooks_url": "https://api.github.com/orgs/sportkit/hooks",
    "issues_url": "https://api.github.com/orgs/sportkit/issues",
    "members_url": "https://api.github.com/orgs/sportkit/members{/member}",
    "public_members_url": "https://api.github.com/orgs/sportkit/public_members{/member}",
    "avatar_url": "https://avatars.githubusercontent.com/u/8416996?v=3",
    "description": "Build your own HTTP JSON APIs using football.db, worldcup.db, etc."
  },
  {
    "login": "writekit",
    "id": 8590186,
    "url": "https://api.github.com/orgs/writekit",
    "repos_url": "https://api.github.com/orgs/writekit/repos",
    "events_url": "https://api.github.com/orgs/writekit/events",
    "hooks_url": "https://api.github.com/orgs/writekit/hooks",
    "issues_url": "https://api.github.com/orgs/writekit/issues",
    "members_url": "https://api.github.com/orgs/writekit/members{/member}",
    "public_members_url": "https://api.github.com/orgs/writekit/public_members{/member}",
    "avatar_url": "https://avatars.githubusercontent.com/u/8590186?v=3",
    "description": "Markdown Tools, Scripts, Themes & More"
  },
  {
    "login": "slidekit",
    "id": 8601012,
    "url": "https://api.github.com/orgs/slidekit",
    "repos_url": "https://api.github.com/orgs/slidekit/repos",
    "events_url": "https://api.github.com/orgs/slidekit/events",
    "hooks_url": "https://api.github.com/orgs/slidekit/hooks",
    "issues_url": "https://api.github.com/orgs/slidekit/issues",
    "members_url": "https://api.github.com/orgs/slidekit/members{/member}",
    "public_members_url": "https://api.github.com/orgs/slidekit/public_members{/member}",
    "avatar_url": "https://avatars.githubusercontent.com/u/8601012?v=3",
    "description": "Slide Show Templates Using HTML5, CSS3 'n' JavaScript"
  },
  {
    "login": "mokkalibs",
    "id": 8940171,
    "url": "https://api.github.com/orgs/mokkalibs",
    "repos_url": "https://api.github.com/orgs/mokkalibs/repos",
    "events_url": "https://api.github.com/orgs/mokkalibs/events",
    "hooks_url": "https://api.github.com/orgs/mokkalibs/hooks",
    "issues_url": "https://api.github.com/orgs/mokkalibs/issues",
    "members_url": "https://api.github.com/orgs/mokkalibs/members{/member}",
    "public_members_url": "https://api.github.com/orgs/mokkalibs/public_members{/member}",
    "avatar_url": "https://avatars.githubusercontent.com/u/8940171?v=3",
    "description": null
  },
  {
    "login": "planet-templates",
    "id": 10121630,
    "url": "https://api.github.com/orgs/planet-templates",
    "repos_url": "https://api.github.com/orgs/planet-templates/repos",
    "events_url": "https://api.github.com/orgs/planet-templates/events",
    "hooks_url": "https://api.github.com/orgs/planet-templates/hooks",
    "issues_url": "https://api.github.com/orgs/planet-templates/issues",
    "members_url": "https://api.github.com/orgs/planet-templates/members{/member}",
    "public_members_url": "https://api.github.com/orgs/planet-templates/public_members{/member}",
    "avatar_url": "https://avatars.githubusercontent.com/u/10121630?v=3",
    "description": "Free Planet Planet Site 'n' Feed Templates"
  },
  {
    "login": "slideshow-templates",
    "id": 10121942,
    "url": "https://api.github.com/orgs/slideshow-templates",
    "repos_url": "https://api.github.com/orgs/slideshow-templates/repos",
    "events_url": "https://api.github.com/orgs/slideshow-templates/events",
    "hooks_url": "https://api.github.com/orgs/slideshow-templates/hooks",
    "issues_url": "https://api.github.com/orgs/slideshow-templates/issues",
    "members_url": "https://api.github.com/orgs/slideshow-templates/members{/member}",
    "public_members_url": "https://api.github.com/orgs/slideshow-templates/public_members{/member}",
    "avatar_url": "https://avatars.githubusercontent.com/u/10121942?v=3",
    "description": "Free Slideshow Templates (in HTML, CSS 'n' JavaScript) - Web Alternative to PowerPoint and Keynote"
  },
  {
    "login": "RubyHabits",
    "id": 10383149,
    "url": "https://api.github.com/orgs/RubyHabits",
    "repos_url": "https://api.github.com/orgs/RubyHabits/repos",
    "events_url": "https://api.github.com/orgs/RubyHabits/events",
    "hooks_url": "https://api.github.com/orgs/RubyHabits/hooks",
    "issues_url": "https://api.github.com/orgs/RubyHabits/issues",
    "members_url": "https://api.github.com/orgs/RubyHabits/members{/member}",
    "public_members_url": "https://api.github.com/orgs/RubyHabits/public_members{/member}",
    "avatar_url": "https://avatars.githubusercontent.com/u/10383149?v=3",
    "description": "A Ruby learning group located in Vienna. Ruby newbies to fully-fledged rubyists, delving into programming and learning ruby together."
  },
  {
    "login": "book-templates",
    "id": 10548511,
    "url": "https://api.github.com/orgs/book-templates",
    "repos_url": "https://api.github.com/orgs/book-templates/repos",
    "events_url": "https://api.github.com/orgs/book-templates/events",
    "hooks_url": "https://api.github.com/orgs/book-templates/hooks",
    "issues_url": "https://api.github.com/orgs/book-templates/issues",
    "members_url": "https://api.github.com/orgs/book-templates/members{/member}",
    "public_members_url": "https://api.github.com/orgs/book-templates/public_members{/member}",
    "avatar_url": "https://avatars.githubusercontent.com/u/10548511?v=3",
    "description": "Free Hypertext Book Templates (in HTML, CSS  'n' JavaScript)"
  },
  {
    "login": "planetjekyll",
    "id": 10807323,
    "url": "https://api.github.com/orgs/planetjekyll",
    "repos_url": "https://api.github.com/orgs/planetjekyll/repos",
    "events_url": "https://api.github.com/orgs/planetjekyll/events",
    "hooks_url": "https://api.github.com/orgs/planetjekyll/hooks",
    "issues_url": "https://api.github.com/orgs/planetjekyll/issues",
    "members_url": "https://api.github.com/orgs/planetjekyll/members{/member}",
    "public_members_url": "https://api.github.com/orgs/planetjekyll/public_members{/member}",
    "avatar_url": "https://avatars.githubusercontent.com/u/10807323?v=3",
    "description": "All the News About the Static Site Generator in Ruby"
  },
  {
    "login": "planetruby",
    "id": 10809106,
    "url": "https://api.github.com/orgs/planetruby",
    "repos_url": "https://api.github.com/orgs/planetruby/repos",
    "events_url": "https://api.github.com/orgs/planetruby/events",
    "hooks_url": "https://api.github.com/orgs/planetruby/hooks",
    "issues_url": "https://api.github.com/orgs/planetruby/issues",
    "members_url": "https://api.github.com/orgs/planetruby/members{/member}",
    "public_members_url": "https://api.github.com/orgs/planetruby/public_members{/member}",
    "avatar_url": "https://avatars.githubusercontent.com/u/10809106?v=3",
    "description": "All the News About Ruby, JRuby, Rubinius, Opal, Rails, Rake, Jekyll, Sinatra, etc."
  },
  {
    "login": "planetbeer",
    "id": 10907957,
    "url": "https://api.github.com/orgs/planetbeer",
    "repos_url": "https://api.github.com/orgs/planetbeer/repos",
    "events_url": "https://api.github.com/orgs/planetbeer/events",
    "hooks_url": "https://api.github.com/orgs/planetbeer/hooks",
    "issues_url": "https://api.github.com/orgs/planetbeer/issues",
    "members_url": "https://api.github.com/orgs/planetbeer/members{/member}",
    "public_members_url": "https://api.github.com/orgs/planetbeer/public_members{/member}",
    "avatar_url": "https://avatars.githubusercontent.com/u/10907957?v=3",
    "description": "News Reader About All Things Beer - Prost, Cheers, Kampai"
  },
  {
    "login": "planetopendata",
    "id": 12104862,
    "url": "https://api.github.com/orgs/planetopendata",
    "repos_url": "https://api.github.com/orgs/planetopendata/repos",
    "events_url": "https://api.github.com/orgs/planetopendata/events",
    "hooks_url": "https://api.github.com/orgs/planetopendata/hooks",
    "issues_url": "https://api.github.com/orgs/planetopendata/issues",
    "members_url": "https://api.github.com/orgs/planetopendata/members{/member}",
    "public_members_url": "https://api.github.com/orgs/planetopendata/public_members{/member}",
    "avatar_url": "https://avatars.githubusercontent.com/u/12104862?v=3",
    "description": "All the News About Open Data incl. Wikidata, Factbook, World Data, Football Data, Tabular Data Packages, SQLite, football.db, beer.db, etc."
  },
  {
    "login": "drjekyllthemes",
    "id": 13346701,
    "url": "https://api.github.com/orgs/drjekyllthemes",
    "repos_url": "https://api.github.com/orgs/drjekyllthemes/repos",
    "events_url": "https://api.github.com/orgs/drjekyllthemes/events",
    "hooks_url": "https://api.github.com/orgs/drjekyllthemes/hooks",
    "issues_url": "https://api.github.com/orgs/drjekyllthemes/issues",
    "members_url": "https://api.github.com/orgs/drjekyllthemes/members{/member}",
    "public_members_url": "https://api.github.com/orgs/drjekyllthemes/public_members{/member}",
    "avatar_url": "https://avatars.githubusercontent.com/u/13346701?v=3",
    "description": "(Yet Another) Static Site Generator Theme Directory - Add Your Theme!"
  },
  {
    "login": "worldclassics",
    "id": 13405489,
    "url": "https://api.github.com/orgs/worldclassics",
    "repos_url": "https://api.github.com/orgs/worldclassics/repos",
    "events_url": "https://api.github.com/orgs/worldclassics/events",
    "hooks_url": "https://api.github.com/orgs/worldclassics/hooks",
    "issues_url": "https://api.github.com/orgs/worldclassics/issues",
    "members_url": "https://api.github.com/orgs/worldclassics/members{/member}",
    "public_members_url": "https://api.github.com/orgs/worldclassics/public_members{/member}",
    "avatar_url": "https://avatars.githubusercontent.com/u/13405489?v=3",
    "description": "The world's greatest (literature) books in .txt"
  },
  {
    "login": "viennahtml",
    "id": 13419070,
    "url": "https://api.github.com/orgs/viennahtml",
    "repos_url": "https://api.github.com/orgs/viennahtml/repos",
    "events_url": "https://api.github.com/orgs/viennahtml/events",
    "hooks_url": "https://api.github.com/orgs/viennahtml/hooks",
    "issues_url": "https://api.github.com/orgs/viennahtml/issues",
    "members_url": "https://api.github.com/orgs/viennahtml/members{/member}",
    "public_members_url": "https://api.github.com/orgs/viennahtml/public_members{/member}",
    "avatar_url": "https://avatars.githubusercontent.com/u/13419070?v=3",
    "description": "Static is the New Dynamic // Jekyll & Friends Meetup in Vienna, Austria  // Join Us (Free) // No Database Required"
  },
  {
    "login": "rubyref",
    "id": 13598290,
    "url": "https://api.github.com/orgs/rubyref",
    "repos_url": "https://api.github.com/orgs/rubyref/repos",
    "events_url": "https://api.github.com/orgs/rubyref/events",
    "hooks_url": "https://api.github.com/orgs/rubyref/hooks",
    "issues_url": "https://api.github.com/orgs/rubyref/issues",
    "members_url": "https://api.github.com/orgs/rubyref/members{/member}",
    "public_members_url": "https://api.github.com/orgs/rubyref/public_members{/member}",
    "avatar_url": "https://avatars.githubusercontent.com/u/13598290?v=3",
    "description": "Quick References (Cheat Sheets) for ActiveRecord, Minitest, Net::HTTP, 'n' Friends"
  },
  {
    "login": "mrhydescripts",
    "id": 13766482,
    "url": "https://api.github.com/orgs/mrhydescripts",
    "repos_url": "https://api.github.com/orgs/mrhydescripts/repos",
    "events_url": "https://api.github.com/orgs/mrhydescripts/events",
    "hooks_url": "https://api.github.com/orgs/mrhydescripts/hooks",
    "issues_url": "https://api.github.com/orgs/mrhydescripts/issues",
    "members_url": "https://api.github.com/orgs/mrhydescripts/members{/member}",
    "public_members_url": "https://api.github.com/orgs/mrhydescripts/public_members{/member}",
    "avatar_url": "https://avatars.githubusercontent.com/u/13766482?v=3",
    "description": "Quick Starter Static Site Scripts - Automate, Automate, Automate - Add Your Script!"
  },
  {
    "login": "sportlabs",
    "id": 14292493,
    "url": "https://api.github.com/orgs/sportlabs",
    "repos_url": "https://api.github.com/orgs/sportlabs/repos",
    "events_url": "https://api.github.com/orgs/sportlabs/events",
    "hooks_url": "https://api.github.com/orgs/sportlabs/hooks",
    "issues_url": "https://api.github.com/orgs/sportlabs/issues",
    "members_url": "https://api.github.com/orgs/sportlabs/members{/member}",
    "public_members_url": "https://api.github.com/orgs/sportlabs/public_members{/member}",
    "avatar_url": "https://avatars.githubusercontent.com/u/14292493?v=3",
    "description": "Upcoming Leagues, Tools & Scripts, And More - Your Contributions Welcome"
  },
  {
    "login": "factbook",
    "id": 14881055,
    "url": "https://api.github.com/orgs/factbook",
    "repos_url": "https://api.github.com/orgs/factbook/repos",
    "events_url": "https://api.github.com/orgs/factbook/events",
    "hooks_url": "https://api.github.com/orgs/factbook/hooks",
    "issues_url": "https://api.github.com/orgs/factbook/issues",
    "members_url": "https://api.github.com/orgs/factbook/members{/member}",
    "public_members_url": "https://api.github.com/orgs/factbook/public_members{/member}",
    "avatar_url": "https://avatars.githubusercontent.com/u/14881055?v=3",
    "description": "Free Open Public Domain Data :: 250+ Country Profiles (Incl. Flags 'n' Maps)"
  },
  {
    "login": "staystatic",
    "id": 16611659,
    "url": "https://api.github.com/orgs/staystatic",
    "repos_url": "https://api.github.com/orgs/staystatic/repos",
    "events_url": "https://api.github.com/orgs/staystatic/events",
    "hooks_url": "https://api.github.com/orgs/staystatic/hooks",
    "issues_url": "https://api.github.com/orgs/staystatic/issues",
    "members_url": "https://api.github.com/orgs/staystatic/members{/member}",
    "public_members_url": "https://api.github.com/orgs/staystatic/public_members{/member}",
    "avatar_url": "https://avatars.githubusercontent.com/u/16611659?v=3",
    "description": "Jekyll  • Middleman • Nanoc • Webgen • Metalsmith • Gatsby • Harp • Nikola • Hugo"
  },
  {
    "login": "statictimes",
    "id": 16964858,
    "url": "https://api.github.com/orgs/statictimes",
    "repos_url": "https://api.github.com/orgs/statictimes/repos",
    "events_url": "https://api.github.com/orgs/statictimes/events",
    "hooks_url": "https://api.github.com/orgs/statictimes/hooks",
    "issues_url": "https://api.github.com/orgs/statictimes/issues",
    "members_url": "https://api.github.com/orgs/statictimes/members{/member}",
    "public_members_url": "https://api.github.com/orgs/statictimes/public_members{/member}",
    "avatar_url": "https://avatars.githubusercontent.com/u/16964858?v=3",
    "description": "Static Site Builder / Generator News • Static is the New Dynamic • Tools / Showcases / Articles / Books / Events & More"
  },
  {
    "login": "henrythemes",
    "id": 17216374,
    "url": "https://api.github.com/orgs/henrythemes",
    "repos_url": "https://api.github.com/orgs/henrythemes/repos",
    "events_url": "https://api.github.com/orgs/henrythemes/events",
    "hooks_url": "https://api.github.com/orgs/henrythemes/hooks",
    "issues_url": "https://api.github.com/orgs/henrythemes/issues",
    "members_url": "https://api.github.com/orgs/henrythemes/members{/member}",
    "public_members_url": "https://api.github.com/orgs/henrythemes/public_members{/member}",
    "avatar_url": "https://avatars.githubusercontent.com/u/17216374?v=3",
    "description": "Free Jekyll Starter Themes - Static Site Templates & Designs"
  },
  {
    "login": "printhtml",
    "id": 17305202,
    "url": "https://api.github.com/orgs/printhtml",
    "repos_url": "https://api.github.com/orgs/printhtml/repos",
    "events_url": "https://api.github.com/orgs/printhtml/events",
    "hooks_url": "https://api.github.com/orgs/printhtml/hooks",
    "issues_url": "https://api.github.com/orgs/printhtml/issues",
    "members_url": "https://api.github.com/orgs/printhtml/members{/member}",
    "public_members_url": "https://api.github.com/orgs/printhtml/public_members{/member}",
    "avatar_url": "https://avatars.githubusercontent.com/u/17305202?v=3",
    "description": "Print Books • Magazines • Newspapers • Letters 'n' More with HTML & CSS"
  },
  {
    "login": "manuscripts",
    "id": 17341388,
    "url": "https://api.github.com/orgs/manuscripts",
    "repos_url": "https://api.github.com/orgs/manuscripts/repos",
    "events_url": "https://api.github.com/orgs/manuscripts/events",
    "hooks_url": "https://api.github.com/orgs/manuscripts/hooks",
    "issues_url": "https://api.github.com/orgs/manuscripts/issues",
    "members_url": "https://api.github.com/orgs/manuscripts/members{/member}",
    "public_members_url": "https://api.github.com/orgs/manuscripts/public_members{/member}",
    "avatar_url": "https://avatars.githubusercontent.com/u/17341388?v=3",
    "description": "A Free Book Format - Write Books in Plain Text (with Markdown)"
  },
  {
    "login": "hydepress",
    "id": 17433501,
    "url": "https://api.github.com/orgs/hydepress",
    "repos_url": "https://api.github.com/orgs/hydepress/repos",
    "events_url": "https://api.github.com/orgs/hydepress/events",
    "hooks_url": "https://api.github.com/orgs/hydepress/hooks",
    "issues_url": "https://api.github.com/orgs/hydepress/issues",
    "members_url": "https://api.github.com/orgs/hydepress/members{/member}",
    "public_members_url": "https://api.github.com/orgs/hydepress/public_members{/member}",
    "avatar_url": "https://avatars.githubusercontent.com/u/17433501?v=3",
    "description": "Free Books about Jekyll 'n' Friends"
  },
  {
    "login": "yukimotopress",
    "id": 17497275,
    "url": "https://api.github.com/orgs/yukimotopress",
    "repos_url": "https://api.github.com/orgs/yukimotopress/repos",
    "events_url": "https://api.github.com/orgs/yukimotopress/events",
    "hooks_url": "https://api.github.com/orgs/yukimotopress/hooks",
    "issues_url": "https://api.github.com/orgs/yukimotopress/issues",
    "members_url": "https://api.github.com/orgs/yukimotopress/members{/member}",
    "public_members_url": "https://api.github.com/orgs/yukimotopress/public_members{/member}",
    "avatar_url": "https://avatars.githubusercontent.com/u/17497275?v=3",
    "description": "Free Books about Ruby & Friends"
  },
  {
    "login": "bookdesigns",
    "id": 17617514,
    "url": "https://api.github.com/orgs/bookdesigns",
    "repos_url": "https://api.github.com/orgs/bookdesigns/repos",
    "events_url": "https://api.github.com/orgs/bookdesigns/events",
    "hooks_url": "https://api.github.com/orgs/bookdesigns/hooks",
    "issues_url": "https://api.github.com/orgs/bookdesigns/issues",
    "members_url": "https://api.github.com/orgs/bookdesigns/members{/member}",
    "public_members_url": "https://api.github.com/orgs/bookdesigns/public_members{/member}",
    "avatar_url": "https://avatars.githubusercontent.com/u/17617514?v=3",
    "description": "One Book, Many Designs - Add Your Design!"
  },
  {
    "login": "quikstart",
    "id": 17684738,
    "url": "https://api.github.com/orgs/quikstart",
    "repos_url": "https://api.github.com/orgs/quikstart/repos",
    "events_url": "https://api.github.com/orgs/quikstart/events",
    "hooks_url": "https://api.github.com/orgs/quikstart/hooks",
    "issues_url": "https://api.github.com/orgs/quikstart/issues",
    "members_url": "https://api.github.com/orgs/quikstart/members{/member}",
    "public_members_url": "https://api.github.com/orgs/quikstart/public_members{/member}",
    "avatar_url": "https://avatars.githubusercontent.com/u/17684738?v=3",
    "description": "Ruby's Scaffolding Tool for New Projects (Gems, Sinatra Apps, Jekyll Themes, etc.) e.g. $ quik new gem or $ qk new sinatra or $ qk n jekyll-theme"
  },
  {
    "login": "bibtxt",
    "id": 17685800,
    "url": "https://api.github.com/orgs/bibtxt",
    "repos_url": "https://api.github.com/orgs/bibtxt/repos",
    "events_url": "https://api.github.com/orgs/bibtxt/events",
    "hooks_url": "https://api.github.com/orgs/bibtxt/hooks",
    "issues_url": "https://api.github.com/orgs/bibtxt/issues",
    "members_url": "https://api.github.com/orgs/bibtxt/members{/member}",
    "public_members_url": "https://api.github.com/orgs/bibtxt/public_members{/member}",
    "avatar_url": "https://avatars.githubusercontent.com/u/17685800?v=3",
    "description": "Bibliographies in Text - BibTeX for the 21st Century (Unicode, etc.) - Books, Articles, etc."
  },
  {
    "login": "funpress",
    "id": 17773305,
    "url": "https://api.github.com/orgs/funpress",
    "repos_url": "https://api.github.com/orgs/funpress/repos",
    "events_url": "https://api.github.com/orgs/funpress/events",
    "hooks_url": "https://api.github.com/orgs/funpress/hooks",
    "issues_url": "https://api.github.com/orgs/funpress/issues",
    "members_url": "https://api.github.com/orgs/funpress/members{/member}",
    "public_members_url": "https://api.github.com/orgs/funpress/public_members{/member}",
    "avatar_url": "https://avatars.githubusercontent.com/u/17773305?v=3",
    "description": "=()=> Free Functional Programming Books about JavaScript & Friends"
  },
  {
    "login": "pagedesigns",
    "id": 17814553,
    "url": "https://api.github.com/orgs/pagedesigns",
    "repos_url": "https://api.github.com/orgs/pagedesigns/repos",
    "events_url": "https://api.github.com/orgs/pagedesigns/events",
    "hooks_url": "https://api.github.com/orgs/pagedesigns/hooks",
    "issues_url": "https://api.github.com/orgs/pagedesigns/issues",
    "members_url": "https://api.github.com/orgs/pagedesigns/members{/member}",
    "public_members_url": "https://api.github.com/orgs/pagedesigns/public_members{/member}",
    "avatar_url": "https://avatars.githubusercontent.com/u/17814553?v=3",
    "description": "One Page, Many Designs - Add Your Design! "
  },
  {
    "login": "jekyll-octopod",
    "id": 19706382,
    "url": "https://api.github.com/orgs/jekyll-octopod",
    "repos_url": "https://api.github.com/orgs/jekyll-octopod/repos",
    "events_url": "https://api.github.com/orgs/jekyll-octopod/events",
    "hooks_url": "https://api.github.com/orgs/jekyll-octopod/hooks",
    "issues_url": "https://api.github.com/orgs/jekyll-octopod/issues",
    "members_url": "https://api.github.com/orgs/jekyll-octopod/members{/member}",
    "public_members_url": "https://api.github.com/orgs/jekyll-octopod/public_members{/member}",
    "avatar_url": "https://avatars.githubusercontent.com/u/19706382?v=3",
    "description": "Podcast publishing plugin for the Static site generator Jekyll"
  },
  {
    "login": "octobook",
    "id": 19760878,
    "url": "https://api.github.com/orgs/octobook",
    "repos_url": "https://api.github.com/orgs/octobook/repos",
    "events_url": "https://api.github.com/orgs/octobook/events",
    "hooks_url": "https://api.github.com/orgs/octobook/hooks",
    "issues_url": "https://api.github.com/orgs/octobook/issues",
    "members_url": "https://api.github.com/orgs/octobook/members{/member}",
    "public_members_url": "https://api.github.com/orgs/octobook/public_members{/member}",
    "avatar_url": "https://avatars.githubusercontent.com/u/19760878?v=3",
    "description": "Book publishing tools 'n' themes for Jekyll"
  },
  {
    "login": "shellpress",
    "id": 20123859,
    "url": "https://api.github.com/orgs/shellpress",
    "repos_url": "https://api.github.com/orgs/shellpress/repos",
    "events_url": "https://api.github.com/orgs/shellpress/events",
    "hooks_url": "https://api.github.com/orgs/shellpress/hooks",
    "issues_url": "https://api.github.com/orgs/shellpress/issues",
    "members_url": "https://api.github.com/orgs/shellpress/members{/member}",
    "public_members_url": "https://api.github.com/orgs/shellpress/public_members{/member}",
    "avatar_url": "https://avatars.githubusercontent.com/u/20123859?v=3",
    "description": "Free Computer Books about Linux & Friends"
  },
  {
    "login": "updownpress",
    "id": 20245932,
    "url": "https://api.github.com/orgs/updownpress",
    "repos_url": "https://api.github.com/orgs/updownpress/repos",
    "events_url": "https://api.github.com/orgs/updownpress/events",
    "hooks_url": "https://api.github.com/orgs/updownpress/hooks",
    "issues_url": "https://api.github.com/orgs/updownpress/issues",
    "members_url": "https://api.github.com/orgs/updownpress/members{/member}",
    "public_members_url": "https://api.github.com/orgs/updownpress/public_members{/member}",
    "avatar_url": "https://avatars.githubusercontent.com/u/20245932?v=3",
    "description": "Free Books about Markup & Markdown"
  },
  {
    "login": "mundimark",
    "id": 20706526,
    "url": "https://api.github.com/orgs/mundimark",
    "repos_url": "https://api.github.com/orgs/mundimark/repos",
    "events_url": "https://api.github.com/orgs/mundimark/events",
    "hooks_url": "https://api.github.com/orgs/mundimark/hooks",
    "issues_url": "https://api.github.com/orgs/mundimark/issues",
    "members_url": "https://api.github.com/orgs/mundimark/members{/member}",
    "public_members_url": "https://api.github.com/orgs/mundimark/public_members{/member}",
    "avatar_url": "https://avatars.githubusercontent.com/u/20706526?v=3",
    "description": "All About Markup & Markdown "
  },
  {
    "login": "opendatajson",
    "id": 23187025,
    "url": "https://api.github.com/orgs/opendatajson",
    "repos_url": "https://api.github.com/orgs/opendatajson/repos",
    "events_url": "https://api.github.com/orgs/opendatajson/events",
    "hooks_url": "https://api.github.com/orgs/opendatajson/hooks",
    "issues_url": "https://api.github.com/orgs/opendatajson/issues",
    "members_url": "https://api.github.com/orgs/opendatajson/members{/member}",
    "public_members_url": "https://api.github.com/orgs/opendatajson/public_members{/member}",
    "avatar_url": "https://avatars.githubusercontent.com/u/23187025?v=3",
    "description": "Free Public Domain Datasets (Incl. football.json, factbook.json 'n' More) - Serve Yourself - No API Key Required  ;-)"
  },
  {
    "login": "footballbook",
    "id": 23198479,
    "url": "https://api.github.com/orgs/footballbook",
    "repos_url": "https://api.github.com/orgs/footballbook/repos",
    "events_url": "https://api.github.com/orgs/footballbook/events",
    "hooks_url": "https://api.github.com/orgs/footballbook/hooks",
    "issues_url": "https://api.github.com/orgs/footballbook/issues",
    "members_url": "https://api.github.com/orgs/footballbook/members{/member}",
    "public_members_url": "https://api.github.com/orgs/footballbook/public_members{/member}",
    "avatar_url": "https://avatars.githubusercontent.com/u/23198479?v=3",
    "description": "National Teams & Tournaments / Clubs & Leagues / Calendar"
  },
  {
    "login": "beerbook",
    "id": 23233034,
    "url": "https://api.github.com/orgs/beerbook",
    "repos_url": "https://api.github.com/orgs/beerbook/repos",
    "events_url": "https://api.github.com/orgs/beerbook/events",
    "hooks_url": "https://api.github.com/orgs/beerbook/hooks",
    "issues_url": "https://api.github.com/orgs/beerbook/issues",
    "members_url": "https://api.github.com/orgs/beerbook/members{/member}",
    "public_members_url": "https://api.github.com/orgs/beerbook/public_members{/member}",
    "avatar_url": "https://avatars.githubusercontent.com/u/23233034?v=3",
    "description": "Beers / Breweries / Brewpubs / Maps 'n' More"
  },
  {
    "login": "worldbook",
    "id": 23438727,
    "url": "https://api.github.com/orgs/worldbook",
    "repos_url": "https://api.github.com/orgs/worldbook/repos",
    "events_url": "https://api.github.com/orgs/worldbook/events",
    "hooks_url": "https://api.github.com/orgs/worldbook/hooks",
    "issues_url": "https://api.github.com/orgs/worldbook/issues",
    "members_url": "https://api.github.com/orgs/worldbook/members{/member}",
    "public_members_url": "https://api.github.com/orgs/worldbook/public_members{/member}",
    "avatar_url": "https://avatars.githubusercontent.com/u/23438727?v=3",
    "description": "Continents  •  Countries  •  Territories  •  States  •  Provinces  •  Cities  •  Towns"
  },
  {
    "login": "publicdomainworks",
    "id": 23472320,
    "url": "https://api.github.com/orgs/publicdomainworks",
    "repos_url": "https://api.github.com/orgs/publicdomainworks/repos",
    "events_url": "https://api.github.com/orgs/publicdomainworks/events",
    "hooks_url": "https://api.github.com/orgs/publicdomainworks/hooks",
    "issues_url": "https://api.github.com/orgs/publicdomainworks/issues",
    "members_url": "https://api.github.com/orgs/publicdomainworks/members{/member}",
    "public_members_url": "https://api.github.com/orgs/publicdomainworks/public_members{/member}",
    "avatar_url": "https://avatars.githubusercontent.com/u/23472320?v=3",
    "description": "No Copyright •  No License •  No Rights Reserved"
  },
  {
    "login": "schemadoc",
    "id": 25107635,
    "url": "https://api.github.com/orgs/schemadoc",
    "repos_url": "https://api.github.com/orgs/schemadoc/repos",
    "events_url": "https://api.github.com/orgs/schemadoc/events",
    "hooks_url": "https://api.github.com/orgs/schemadoc/hooks",
    "issues_url": "https://api.github.com/orgs/schemadoc/issues",
    "members_url": "https://api.github.com/orgs/schemadoc/members{/member}",
    "public_members_url": "https://api.github.com/orgs/schemadoc/public_members{/member}",
    "avatar_url": "https://avatars.githubusercontent.com/u/25107635?v=3",
    "description": "document your database schemas (tables, columns, etc.)"
  },
  {
    "login": "feedparser",
    "id": 25605819,
    "url": "https://api.github.com/orgs/feedparser",
    "repos_url": "https://api.github.com/orgs/feedparser/repos",
    "events_url": "https://api.github.com/orgs/feedparser/events",
    "hooks_url": "https://api.github.com/orgs/feedparser/hooks",
    "issues_url": "https://api.github.com/orgs/feedparser/issues",
    "members_url": "https://api.github.com/orgs/feedparser/members{/member}",
    "public_members_url": "https://api.github.com/orgs/feedparser/public_members{/member}",
    "avatar_url": "https://avatars.githubusercontent.com/u/25605819?v=3",
    "description": "feedparser gem - web feed parser and normalizer (Atom, RSS 2.0, etc.)"
  },
  {
    "login": "plutolive",
    "id": 25607686,
    "url": "https://api.github.com/orgs/plutolive",
    "repos_url": "https://api.github.com/orgs/plutolive/repos",
    "events_url": "https://api.github.com/orgs/plutolive/events",
    "hooks_url": "https://api.github.com/orgs/plutolive/hooks",
    "issues_url": "https://api.github.com/orgs/plutolive/issues",
    "members_url": "https://api.github.com/orgs/plutolive/members{/member}",
    "public_members_url": "https://api.github.com/orgs/plutolive/public_members{/member}",
    "avatar_url": "https://avatars.githubusercontent.com/u/25607686?v=3",
    "description": "Planet News (Feed) Reader Web Apps - Starter, Live, Admin, etc."
  }
]