{
  "full_name": "pixelartexchange/originals",
  "created_at": "2015-01-08T08:25:27Z",
  "updated_at": "2022-06-14T19:19:02Z",
  "pushed_at": "2022-06-09T11:59:33Z",
  "size": 161,
  "description": "Factory of Modern Originals (FoMO) - Do-It-Yourself (DIY) Yes, You Can! - Fab(criate) Your Own Unique (Pixel) Artworks w/ Text Attributes (Via Built-In Spritesheets) Incl. 2X/4X/8X Zoom for Bigger Sizes And More",
  "language": "Ruby",
  "history": {
    "2022-06-01": {
      "stargazers_count": 18,
      "forks_count": 0
    },
    "2022-06-15": {
      "stargazers_count": 20,
      "forks_count": 1
    }
  },
  "commits": [
    {
      "committer": {
        "date": "2022-06-09T11:59:27Z",
        "name": "Gerald Bauer"
      },
      "author": {
        "date": "2022-06-09T11:59:27Z",
        "name": "Gerald Bauer"
      },
      "message": "up"
    }
  ],
  "topics": [
    "pixelart",
    "24px",
    "coolcats",
    "doge",
    "punks",
    "shiba-inu",
    "marilyns",
    "phunks",
    "fomo",
    "moonbirds",
    "owls"
  ],
  "languages": {
    "Ruby": 23290
  },
  "traffic": {
    "summary": {
      "views": {
        "count": 169,
        "uniques": 14
      },
      "clones": {
        "count": 80,
        "uniques": 27
      },
      "paths": [
        {
          "path": "/pixelartexchange/originals",
          "title": "pixelartexchange/originals: Factory of Modern Originals (FoMO) - Do-It-Yourse...",
          "count": 111,
          "uniques": 14
        },
        {
          "path": "/pixelartexchange/originals/tree/master/i",
          "title": "originals/i at master · pixelartexchange/originals · GitHub",
          "count": 8,
          "uniques": 3
        },
        {
          "path": "/pixelartexchange/originals/tree/master/lib",
          "title": "originals/lib at master · pixelartexchange/originals · GitHub",
          "count": 7,
          "uniques": 3
        },
        {
          "path": "/pixelartexchange/originals/tree/master/bin",
          "title": "originals/bin at master · pixelartexchange/originals · GitHub",
          "count": 5,
          "uniques": 3
        },
        {
          "path": "/pixelartexchange/originals/tree/master/lib/originals",
          "title": "originals/lib/originals at master · pixelartexchange/originals · GitHub",
          "count": 5,
          "uniques": 3
        },
        {
          "path": "/pixelartexchange/originals/tree/master/sandbox",
          "title": "originals/sandbox at master · pixelartexchange/originals · GitHub",
          "count": 4,
          "uniques": 2
        },
        {
          "path": "/pixelartexchange/originals/blob/master/README.md",
          "title": "originals/README.md at master · pixelartexchange/originals",
          "count": 4,
          "uniques": 1
        },
        {
          "path": "/pixelartexchange/originals/graphs/traffic",
          "title": "Traffic · pixelartexchange/originals",
          "count": 3,
          "uniques": 1
        },
        {
          "path": "/pixelartexchange/originals/blob/master/lib/originals.rb",
          "title": "originals/originals.rb at master · pixelartexchange/originals",
          "count": 2,
          "uniques": 2
        },
        {
          "path": "/pixelartexchange/originals/blob/master/lib/originals/tool.rb",
          "title": "originals/tool.rb at master · pixelartexchange/originals",
          "count": 2,
          "uniques": 1
        }
      ],
      "referrers": [
        {
          "referrer": "github.com",
          "count": 70,
          "uniques": 10
        },
        {
          "referrer": "old.reddit.com",
          "count": 53,
          "uniques": 5
        },
        {
          "referrer": "rubydoc.info",
          "count": 5,
          "uniques": 1
        },
        {
          "referrer": "reddit.com",
          "count": 4,
          "uniques": 2
        },
        {
          "referrer": "rubygems.org",
          "count": 3,
          "uniques": 1
        },
        {
          "referrer": "Google",
          "count": 1,
          "uniques": 1
        },
        {
          "referrer": "intellizoo.izoolabs.com",
          "count": 1,
          "uniques": 1
        }
      ]
    },
    "history": {
      "2022-05-19": {
        "views": {
          "count": 1,
          "uniques": 1
        },
        "clones": {
          "count": 1,
          "uniques": 1
        }
      },
      "2022-05-22": {
        "views": {
          "count": 2,
          "uniques": 2
        },
        "clones": {
          "count": 2,
          "uniques": 2
        }
      },
      "2022-05-29": {
        "views": {
          "count": 28,
          "uniques": 2
        },
        "clones": {
          "count": 16,
          "uniques": 13
        }
      },
      "2022-05-30": {
        "views": {
          "count": 60,
          "uniques": 1
        },
        "clones": {
          "count": 16,
          "uniques": 10
        }
      },
      "2022-05-31": {
        "views": {
          "count": 29,
          "uniques": 4
        },
        "clones": {
          "count": 8,
          "uniques": 5
        }
      },
      "2022-06-01": {
        "views": {
          "count": 6,
          "uniques": 1
        },
        "clones": {
          "count": 7,
          "uniques": 5
        }
      },
      "2022-05-20": {
        "clones": {
          "count": 1,
          "uniques": 1
        }
      },
      "2022-05-21": {
        "clones": {
          "count": 2,
          "uniques": 2
        }
      },
      "2022-05-23": {
        "clones": {
          "count": 3,
          "uniques": 3
        }
      },
      "2022-05-24": {
        "clones": {
          "count": 1,
          "uniques": 1
        }
      },
      "2022-05-25": {
        "clones": {
          "count": 3,
          "uniques": 2
        }
      },
      "2022-05-26": {
        "clones": {
          "count": 1,
          "uniques": 1
        }
      },
      "2022-05-27": {
        "clones": {
          "count": 1,
          "uniques": 1
        }
      },
      "2022-05-28": {
        "clones": {
          "count": 1,
          "uniques": 1
        }
      },
      "2022-06-02": {
        "views": {
          "count": 8,
          "uniques": 2
        },
        "clones": {
          "count": 14,
          "uniques": 6
        }
      },
      "2022-06-03": {
        "views": {
          "count": 22,
          "uniques": 2
        },
        "clones": {
          "count": 2,
          "uniques": 2
        }
      },
      "2022-06-04": {
        "views": {
          "count": 9,
          "uniques": 2
        },
        "clones": {
          "count": 2,
          "uniques": 2
        }
      },
      "2022-06-05": {
        "views": {
          "count": 51,
          "uniques": 3
        },
        "clones": {
          "count": 1,
          "uniques": 1
        }
      },
      "2022-06-06": {
        "views": {
          "count": 31,
          "uniques": 1
        },
        "clones": {
          "count": 33,
          "uniques": 12
        }
      },
      "2022-06-07": {
        "views": {
          "count": 5,
          "uniques": 1
        },
        "clones": {
          "count": 1,
          "uniques": 1
        }
      },
      "2022-06-09": {
        "views": {
          "count": 19,
          "uniques": 3
        },
        "clones": {
          "count": 14,
          "uniques": 8
        }
      },
      "2022-06-10": {
        "views": {
          "count": 7,
          "uniques": 2
        },
        "clones": {
          "count": 3,
          "uniques": 3
        }
      },
      "2022-06-11": {
        "views": {
          "count": 12,
          "uniques": 2
        },
        "clones": {
          "count": 1,
          "uniques": 1
        }
      },
      "2022-06-13": {
        "views": {
          "count": 4,
          "uniques": 3
        },
        "clones": {
          "count": 3,
          "uniques": 2
        }
      },
      "2022-06-14": {
        "views": {
          "count": 1,
          "uniques": 1
        },
        "clones": {
          "count": 1,
          "uniques": 1
        }
      },
      "2022-06-08": {
        "clones": {
          "count": 2,
          "uniques": 2
        }
      },
      "2022-06-12": {
        "clones": {
          "count": 2,
          "uniques": 2
        }
      },
      "2022-06-15": {
        "clones": {
          "count": 1,
          "uniques": 1
        }
      }
    }
  }
}